kwot/__init__.py
kwot/main.py
kwot/quoter.py
kwot/quotes.json
kwot-0.0.2.data/data/quotes.json
kwot-0.0.2.dist-info/LICENSE
kwot-0.0.2.dist-info/METADATA
kwot-0.0.2.dist-info/WHEEL
kwot-0.0.2.dist-info/entry_points.txt
kwot-0.0.2.dist-info/top_level.txt
kwot-0.0.2.dist-info/RECORD
