Metadata-Version: 2.1
Name: kwot
Version: 0.0.2
Summary: An awesome random quote generator
Home-page: https://github.com/rkshrksh/kwot
Author: Rakesh Gautam
Author-email: rkshrkshme@gmail.com
License: UNKNOWN
Platform: UNKNOWN
Requires-Python: >=3.6
Requires-Dist: Click
